collectiondict/__init__.py
collectiondict/_collectiondict.py
collectiondict/_reverse_mapping.py
collectiondict/_reverse_multimapping.py
collectiondict/py.typed
collectiondict-0.5.0.dist-info/LICENSE
collectiondict-0.5.0.dist-info/METADATA
collectiondict-0.5.0.dist-info/WHEEL
collectiondict-0.5.0.dist-info/RECORD
